replimap/__init__.py
replimap/main.py
replimap/audit/__init__.py
replimap/audit/checkov_runner.py
replimap/audit/classifier.py
replimap/audit/engine.py
replimap/audit/exporters.py
replimap/audit/fix_suggestions.py
replimap/audit/hooks.py
replimap/audit/models.py
replimap/audit/renderer.py
replimap/audit/reporter.py
replimap/audit/soc2_mapping.py
replimap/audit/terminal_reporter.py
replimap/audit/trust_center.py
replimap/audit/remediation/__init__.py
replimap/audit/remediation/generator.py
replimap/audit/remediation/models.py
replimap/audit/remediation/templates/__init__.py
replimap/audit/remediation/templates/ec2.py
replimap/audit/remediation/templates/kms.py
replimap/audit/remediation/templates/rds.py
replimap/audit/remediation/templates/s3.py
replimap/audit/templates/audit_report.html.j2
replimap/blast/__init__.py
replimap/blast/graph_builder.py
replimap/blast/impact_calculator.py
replimap/blast/models.py
replimap/blast/reporter.py
replimap/cache/__init__.py
replimap/cache/snapshots.py
replimap/cli/__init__.py
replimap/cli/completers.py
replimap/cli/completion.py
replimap/cli/config.py
replimap/cli/context.py
replimap/cli/error_catalog.py
replimap/cli/error_renderer.py
replimap/cli/errors.py
replimap/cli/output.py
replimap/cli/state.py
replimap/cli/telemetry.py
replimap/cli/commands/__init__.py
replimap/cli/commands/analyze.py
replimap/cli/commands/audit.py
replimap/cli/commands/cache.py
replimap/cli/commands/clone.py
replimap/cli/commands/codify.py
replimap/cli/commands/completion.py
replimap/cli/commands/cost.py
replimap/cli/commands/deps.py
replimap/cli/commands/doctor.py
replimap/cli/commands/dr.py
replimap/cli/commands/drift.py
replimap/cli/commands/explain.py
replimap/cli/commands/graph.py
replimap/cli/commands/iam.py
replimap/cli/commands/license.py
replimap/cli/commands/load.py
replimap/cli/commands/profiles.py
replimap/cli/commands/remediate.py
replimap/cli/commands/scan.py
replimap/cli/commands/snapshot.py
replimap/cli/commands/transfer.py
replimap-0.3.29.dist-info/METADATA
replimap-0.3.29.dist-info/WHEEL
replimap-0.3.29.dist-info/entry_points.txt
replimap-0.3.29.dist-info/licenses/LICENSE
replimap-0.3.29.dist-info/RECORD
