Metadata-Version: 2.4
Name: replimap
Version: 0.3.29
Summary: AWS Infrastructure Intelligence Engine — Scan, Understand, Transform
Project-URL: Homepage, https://replimap.com
Project-URL: Documentation, https://replimap.com/docs
Project-URL: Repository, https://github.com/RepliMap/replimap
Project-URL: Issues, https://github.com/RepliMap/replimap/issues
Project-URL: Changelog, https://github.com/RepliMap/replimap/blob/main/CHANGELOG.md
Author-email: David Lu <david@replimap.com>
Maintainer-email: David Lu <david@replimap.com>
License: Proprietary
License-File: LICENSE
Keywords: audit,aws,compliance,devops,infrastructure,replication,security,soc2,staging,terraform
Classifier: Development Status :: 3 - Alpha
Classifier: Intended Audience :: Developers
Classifier: Intended Audience :: System Administrators
Classifier: License :: Other/Proprietary License
Classifier: Operating System :: OS Independent
Classifier: Programming Language :: Python :: 3
Classifier: Programming Language :: Python :: 3.10
Classifier: Programming Language :: Python :: 3.11
Classifier: Programming Language :: Python :: 3.12
Classifier: Programming Language :: Python :: 3.13
Classifier: Programming Language :: Python :: 3.14
Classifier: Topic :: Software Development :: Code Generators
Classifier: Topic :: System :: Systems Administration
Requires-Python: >=3.10
Requires-Dist: aiobotocore>=2.5.0
Requires-Dist: boto3>=1.28.0
Requires-Dist: httpx>=0.25.0
Requires-Dist: jinja2>=3.1.0
Requires-Dist: networkx>=3.0
Requires-Dist: pyyaml>=6.0.0
Requires-Dist: rich>=13.0.0
Requires-Dist: structlog>=24.0.0
Requires-Dist: typer[all]>=0.9.0
Requires-Dist: zstandard>=0.21.0
Provides-Extra: dev
Requires-Dist: beautifulsoup4>=4.12.0; extra == 'dev'
Requires-Dist: boto3-stubs[ec2,rds,s3,sts]>=1.28.0; extra == 'dev'
Requires-Dist: html5lib>=1.1; extra == 'dev'
Requires-Dist: lxml>=5.0.0; extra == 'dev'
Requires-Dist: mypy>=1.0.0; extra == 'dev'
Requires-Dist: pytest-asyncio>=0.21.0; extra == 'dev'
Requires-Dist: pytest-cov>=4.0.0; extra == 'dev'
Requires-Dist: pytest>=7.0.0; extra == 'dev'
Requires-Dist: ruff>=0.1.0; extra == 'dev'
Requires-Dist: types-pyyaml>=6.0.0; extra == 'dev'
Requires-Dist: vcrpy>=6.0.0; extra == 'dev'
